{
    "All's_Well_That_Ends_Well": "",
    "Antony_and_Cleopatra": "",
    "As_You_Like_It": "",
    "Comedy_of_Errors": "",
    "Coriolanus": "",
    "Cymbeline": "",
    "Hamlet": "",
    "Henry_IV,_Part_I": "",
    "Henry_IV,_Part_II": "",
    "Henry_V": "",
    "Henry_VI,_Part_I": "",
    "Henry_VI,_Part_II": "",
    "Henry_VI,_Part_III": "",
    "Henry_VIII": "",
    "Julius_Caesar": "",
    "King_John": "",
    "King_Lear": "",
    "Love's_Labour's_Lost": "",
    "Macbeth": "",
    "Measure_for_Measure": "",
    "Merchant_of_Venice": "",
    "Merry_Wives_of_Windsor": "",
    "Midsummer_Night's_Dream": "",
    "Much_Ado_about_Nothing": "",
    "Othello": "",
    "Pericles": "",
    "Richard_II": "",
    "Richard_III": "",
    "Romeo_and_Juliet": "",
    "Taming_of_the_Shrew": "",
    "Tempest": "",
    "Timon_of_Athens": "",
    "Titus_Andronicus": "",
    "Troilus_and_Cressida": "",
    "Twelfth_Night": "",
    "Two_Gentlemen_of_Verona": "",
    "Winter's_Tale": "",
    "Sonnet_18": ""
  }
